<?xml version="1.0" encoding="UTF-8" standalone="yes"?>
<trpDocMetadata>
    <docId>1385685</docId>
    <title>CH_ACV_P_RENE_MONOD_090</title>
    <uploadTimestamp>1680607963042</uploadTimestamp>
    <uploader>titayna.kauffmann@gmail.com</uploader>
    <uploaderId>115119</uploaderId>
    <nrOfPages>1</nrOfPages>
    <pageId>53674064</pageId>
    <url>https://files.transkribus.eu/Get?fileType=view&amp;id=ZDMAIRCLWHWSLOCENVDKTOPL</url>
    <thumbUrl>https://files.transkribus.eu/Get?fileType=thumb&amp;id=ZDMAIRCLWHWSLOCENVDKTOPL</thumbUrl>
    <status>0</status>
    <fimgStoreColl>TrpDoc_DEA_1385685</fimgStoreColl>
    <origDocId>0</origDocId>
    <collectionList>
        <colList>
            <colId>185684</colId>
            <colName>Transcriptions</colName>
            <description>created by titayna.kauffmann@gmail.com</description>
            <crowdsourcing>false</crowdsourcing>
            <elearning>false</elearning>
            <nrOfDocuments>0</nrOfDocuments>
        </colList>
    </collectionList>
</trpDocMetadata>
